centurypy/__init__.py
centurypy/century.py
centurypy/genetic.py
centurypy/main.py
centurypy-1.0.5.dist-info/LICENSE
centurypy-1.0.5.dist-info/METADATA
centurypy-1.0.5.dist-info/WHEEL
centurypy-1.0.5.dist-info/top_level.txt
centurypy-1.0.5.dist-info/RECORD
