Metadata-Version: 2.1
Name: centurypy
Version: 1.0.5
Summary: Library to train and run the CENTURY (Soil Organic Matter) model
Home-page: https://github.com/vivas24/centurypy
Author: Gerardo Vivas
Author-email: vivas.fermin24@gmail.com
License: MIT
License-File: LICENSE
Requires-Dist: numpy
Requires-Dist: pandas
Requires-Dist: scipy
